setup.py
dsnd_probability_sabelo/Binomialdistribution.py
dsnd_probability_sabelo/Gaussiandistribution.py
dsnd_probability_sabelo/Generaldistribution.py
dsnd_probability_sabelo/__init__.py
dsnd_probability_sabelo.egg-info/PKG-INFO
dsnd_probability_sabelo.egg-info/SOURCES.txt
dsnd_probability_sabelo.egg-info/dependency_links.txt
dsnd_probability_sabelo.egg-info/not-zip-safe
dsnd_probability_sabelo.egg-info/top_level.txt