Metadata-Version: 1.0
Name: dsnd-probability-sabelo
Version: 1.2
Summary: Gaussian and Binomial distributions
Home-page: UNKNOWN
Author: Sabelo Sibanda
Author-email: myemail@something.com
License: UNKNOWN
Platform: UNKNOWN
